livegraph/__init__.py
livegraph/livegraph.py
jupyter_live_graph-0.1.0.dist-info/LICENSE
jupyter_live_graph-0.1.0.dist-info/METADATA
jupyter_live_graph-0.1.0.dist-info/WHEEL
jupyter_live_graph-0.1.0.dist-info/top_level.txt
jupyter_live_graph-0.1.0.dist-info/RECORD
