Metadata-Version: 2.1
Name: jupyter-live-graph
Version: 0.1.0
Summary: Create and update graphs live in Jupyter
Home-page: https://dav-ell.github.io/jupyter-live-graph
Author: David E
Author-email: delliott537@gmail.com
License: MIT
Platform: UNKNOWN
Classifier: Programming Language :: Python :: 3
Classifier: License :: OSI Approved :: MIT License
Classifier: Operating System :: OS Independent
Requires-Python: >=3.4
Requires-Dist: matplotlib
